zengrad_tensorflow/__init__.py
zengrad_tensorflow/zengrad_tensorflow.py
zengrad_tensorflow-0.0.2.dist-info/METADATA
zengrad_tensorflow-0.0.2.dist-info/WHEEL
zengrad_tensorflow-0.0.2.dist-info/top_level.txt
zengrad_tensorflow-0.0.2.dist-info/RECORD
