Metadata-Version: 2.1
Name: zengrad-tensorflow
Version: 0.0.2
Summary: ZenGrad Optimizer - TensorFlow
Home-page: https://github.com/XenReZ/ZenGrad-TensorFlow
Author: Murumuri Naga Poorni
Author-email: poorni.m0405@gmail.com
License: Apache-2.0
Classifier: Programming Language :: Python :: 3
Classifier: License :: OSI Approved :: Apache Software License
Classifier: Operating System :: OS Independent
Classifier: Intended Audience :: Developers
Classifier: Intended Audience :: Science/Research
Classifier: Topic :: Scientific/Engineering :: Artificial Intelligence
Requires-Python: >=3.6
Requires-Dist: tensorflow>=2.10.0
Requires-Dist: keras>=2.10.0
